LICENSE
README.md
setup.py
partycls/__init__.py
partycls/cell.py
partycls/clustering.py
partycls/dim_reduction.py
partycls/feature_scaling.py
partycls/helpers.py
partycls/neighbors.f90
partycls/particle.py
partycls/system.py
partycls/trajectory.py
partycls/workflow.py
partycls.egg-info/PKG-INFO
partycls.egg-info/SOURCES.txt
partycls.egg-info/dependency_links.txt
partycls.egg-info/requires.txt
partycls.egg-info/top_level.txt
partycls/core/__init__.py
partycls/core/_version.py
partycls/core/utils.py
partycls/descriptors/__init__.py
partycls/descriptors/averaged_bo.py
partycls/descriptors/ba.py
partycls/descriptors/bo.py
partycls/descriptors/compactness.py
partycls/descriptors/coordination.py
partycls/descriptors/descriptor.py
partycls/descriptors/dscribe.py
partycls/descriptors/radial.py
partycls/descriptors/radial_bo.py
partycls/descriptors/realspace.f90
partycls/descriptors/smoothed_ba.py
partycls/descriptors/smoothed_bo.py
partycls/descriptors/tetrahedrality.py
tests/test_atooms.py
tests/test_clustering.py
tests/test_descriptors.py
tests/test_helpers.py
tests/test_mdtraj.py
tests/test_trajectory.py