Metadata-Version: 2.1
Name: partycls
Version: 2.0.2
Summary: Unsupervised learning of the structure of particulate systems
Home-page: https://github.com/jorisparet/partycls
Download-URL: https://pypi.org/project/partycls
Author: Joris Paret
Author-email: joris.paret@gmail.com
Maintainer: Joris Paret
License: GPLv3
Keywords: physics,condensed matter,structure,machine learning,unsupervised,clustering,molecular dynamics,particle,descriptor,radial,angular,correlation
Classifier: License :: OSI Approved :: GNU General Public License v3 (GPLv3)
Classifier: Development Status :: 5 - Production/Stable
Classifier: Intended Audience :: Science/Research
Classifier: Programming Language :: Python :: 3
Classifier: Programming Language :: Python :: 3.6
Classifier: Programming Language :: Python :: 3.7
Classifier: Programming Language :: Python :: 3.8
Classifier: Programming Language :: Python :: 3.9
Classifier: Topic :: Scientific/Engineering :: Physics
License-File: LICENSE
Requires-Dist: numpy
Requires-Dist: scikit-learn
